megan/bin/__init__.py
megan/bin/acquire.py
megan/bin/eval.py
megan/bin/featurize.py
megan/bin/train.py
megan/src/__init__.py
megan/src/config.py
megan/src/get_instances.py
megan/src/datasets/__init__.py
megan/src/datasets/uspto_50k.py
megan/src/datasets/uspto_full.py
megan/src/datasets/uspto_mit.py
megan/src/datasets/util.py
megan/src/feat/__init__.py
megan/src/feat/featurize.py
megan/src/feat/find_properties.py
megan/src/feat/graph_features.py
megan/src/feat/megan_graph.py
megan/src/feat/mol_graph.py
megan/src/feat/reaction_actions.py
megan/src/feat/ring_actions.py
megan/src/feat/utils.py
megan/src/feat/vocabulary.py
megan/src/model/__init__.py
megan/src/model/beam_search.py
megan/src/model/megan.py
megan/src/model/megan_utils.py
megan/src/model/utils.py
megan/src/model/graph/__init__.py
megan/src/model/graph/gat.py
megan/src/model/megan_modules/__init__.py
megan/src/model/megan_modules/decoder.py
megan/src/model/megan_modules/encoder.py
megan/src/split/__init__.py
megan/src/split/basic_splits.py
megan/src/utils/__init__.py
megan/src/utils/dispatch_utils.py
syntheseus_megan-0.2.0.dist-info/licenses/LICENSE
syntheseus_megan-0.2.0.dist-info/METADATA
syntheseus_megan-0.2.0.dist-info/WHEEL
syntheseus_megan-0.2.0.dist-info/top_level.txt
syntheseus_megan-0.2.0.dist-info/RECORD
