Metadata-Version: 2.4
Name: syntheseus-megan
Version: 0.2.0
Summary: Fork of MEGAN for use in the syntheseus library
Project-URL: Repository, https://github.com/kmaziarz/megan
License-File: LICENSE
Requires-Dist: gin-config==0.3.0
Requires-Dist: gitpython
Requires-Dist: tensorflow==2.20.0
Requires-Dist: torchtext==0.5.0
Requires-Dist: scipy
Dynamic: license-file
